Workbook

Sheet Données
A1: SAVERDEV DURABLE — Données mensuelles (exercice 2026)
A3: Mois | B3: Bovins actifs | C3: Achats | D3: Ventes | E3: Mortalité | F3: Valeur cheptel | G3: Sacs consommés | H3: Coût alimentation | I3: Chiffre d'affaires | J3: Coût d'achat (vendus) | K3: Coût engraissement (vendus) | L3: Marge totale | M3: Coût alim/tête | N3: Marge/tête | O3: Financement accordé | P3: Financement utilisé (cumul) | Q3: Trésorerie | R3: Taux util. fin. | T3: Structure des coûts (cumul)
A4: Janv. | L4: =I4-J4-K4 -> 0 | M4: =IF(B4=0,0,H4/B4) -> 0 | N4: =IF(D4=0,0,L4/D4) -> 0 | O4: 14775000 | R4: =IF(O4=0,0,P4/O4) -> 0 | T4: Achat des bovins | U4: =SUM(J4:J15) -> 0
A5: Févr. | L5: =I5-J5-K5 -> 0 | M5: =IF(B5=0,0,H5/B5) -> 0 | N5: =IF(D5=0,0,L5/D5) -> 0 | R5: =IF(O5=0,0,P5/O5) -> 0 | T5: Alimentation | U5: =SUM(H4:H15) -> 0
A6: Mars | L6: =I6-J6-K6 -> 0 | M6: =IF(B6=0,0,H6/B6) -> 0 | N6: =IF(D6=0,0,L6/D6) -> 0 | R6: =IF(O6=0,0,P6/O6) -> 0 | T6: Engraissement (autres) | U6: =SUM(K4:K15) -> 0
A7: Avr. | L7: =I7-J7-K7 -> 0 | M7: =IF(B7=0,0,H7/B7) -> 0 | N7: =IF(D7=0,0,L7/D7) -> 0 | R7: =IF(O7=0,0,P7/O7) -> 0
A8: Mai | L8: =I8-J8-K8 -> 0 | M8: =IF(B8=0,0,H8/B8) -> 0 | N8: =IF(D8=0,0,L8/D8) -> 0 | R8: =IF(O8=0,0,P8/O8) -> 0
A9: Juin | L9: =I9-J9-K9 -> 0 | M9: =IF(B9=0,0,H9/B9) -> 0 | N9: =IF(D9=0,0,L9/D9) -> 0 | R9: =IF(O9=0,0,P9/O9) -> 0
A10: Juil. | L10: =I10-J10-K10 -> 0 | M10: =IF(B10=0,0,H10/B10) -> 0 | N10: =IF(D10=0,0,L10/D10) -> 0 | R10: =IF(O10=0,0,P10/O10) -> 0
A11: Août | L11: =I11-J11-K11 -> 0 | M11: =IF(B11=0,0,H11/B11) -> 0 | N11: =IF(D11=0,0,L11/D11) -> 0 | R11: =IF(O11=0,0,P11/O11) -> 0
A12: Sept. | L12: =I12-J12-K12 -> 0 | M12: =IF(B12=0,0,H12/B12) -> 0 | N12: =IF(D12=0,0,L12/D12) -> 0 | R12: =IF(O12=0,0,P12/O12) -> 0
A13: Oct. | L13: =I13-J13-K13 -> 0 | M13: =IF(B13=0,0,H13/B13) -> 0 | N13: =IF(D13=0,0,L13/D13) -> 0 | R13: =IF(O13=0,0,P13/O13) -> 0
A14: Nov. | L14: =I14-J14-K14 -> 0 | M14: =IF(B14=0,0,H14/B14) -> 0 | N14: =IF(D14=0,0,L14/D14) -> 0 | R14: =IF(O14=0,0,P14/O14) -> 0
A15: Déc. | L15: =I15-J15-K15 -> 0 | M15: =IF(B15=0,0,H15/B15) -> 0 | N15: =IF(D15=0,0,L15/D15) -> 0 | R15: =IF(O15=0,0,P15/O15) -> 0
A16: TOTAL / Fin | B16: =B15 -> 0 | C16: =SUM(C4:C15) -> 0 | D16: =SUM(D4:D15) -> 0 | E16: =SUM(E4:E15) -> 0 | H16: =SUM(H4:H15) -> 0 | I16: =SUM(I4:I15) -> 0 | J16: =SUM(J4:J15) -> 0 | K16: =SUM(K4:K15) -> 0 | L16: =SUM(L4:L15) -> 0 | Q16: =Q15 -> 0

Sheet Tableau de Bord
B1: SAVERDEV DURABLE — Tableau de bord
B3: Reporting mensuel destiné au bailleur · exercice 2026 · montants en FCFA
B5: Bovins actifs (fin) | E5: Chiffre d'affaires cumulé | H5: Marge totale cumulée | K5: Marge moyenne / tête | N5: Taux d'utilisation fin. | Q5: Trésorerie disponible
B6: =Données!B15 -> 0 | E6: =Données!I16 -> 0 | H6: =Données!L16 -> 0 | K6: =IF(Données!D16=0,0,Données!L16/Données!D16) -> 0 | N6: =Données!R15 -> 0 | Q6: =Données!Q15 -> 0
